{
    "predictions": [
        {
            "class": "bed",
            "confidence": 0.9582505822181702,
            "x": 594.8167724609375,
            "y": 391.4317626953125,
            "width": 87.37945556640625,
            "height": 77.88162231445312,
            "keypoints": [
                {
                    "x": 592.4271240234375,
                    "y": 427.98553466796875,
                    "confidence": 0.999976634979248,
                    "class_id": 0,
                    "class": "bottom"
                },
                {
                    "x": 592.174560546875,
                    "y": 353.529541015625,
                    "confidence": 0.9999947547912598,
                    "class_id": 1,
                    "class": "top"
                }
            ]
        },
        {
            "class": "bed",
            "confidence": 0.9558853507041931,
            "x": 132.97903442382812,
            "y": 279.5189514160156,
            "width": 61.423500061035156,
            "height": 116.33439636230469,
            "keypoints": [
                {
                    "x": 161.47201538085938,
                    "y": 275.8445129394531,
                    "confidence": 0.9999904632568359,
                    "class_id": 0,
                    "class": "bottom"
                },
                {
                    "x": 104.5053939819336,
                    "y": 276.14141845703125,
                    "confidence": 0.9999946355819702,
                    "class_id": 1,
                    "class": "top"
                }
            ]
        },
        {
            "class": "bed",
            "confidence": 0.9546418786048889,
            "x": 608.0938110351562,
            "y": 262.93487548828125,
            "width": 75.2574462890625,
            "height": 76.57652282714844,
            "keypoints": [
                {
                    "x": 608.2586059570312,
                    "y": 300.65557861328125,
                    "confidence": 0.9999709129333496,
                    "class_id": 0,
                    "class": "bottom"
                },
                {
                    "x": 608.9202270507812,
                    "y": 225.08802795410156,
                    "confidence": 0.9999866485595703,
                    "class_id": 1,
                    "class": "top"
                }
            ]
        },
        {
            "class": "bed",
            "confidence": 0.9453420639038086,
            "x": 582.4207763671875,
            "y": 126.97712707519531,
            "width": 57.88824462890625,
            "height": 110.35924530029297,
            "keypoints": [
                {
                    "x": 555.4996337890625,
                    "y": 124.2928695678711,
                    "confidence": 0.9999784231185913,
                    "class_id": 0,
                    "class": "bottom"
                },
                {
                    "x": 607.4959106445312,
                    "y": 124.16265869140625,
                    "confidence": 0.9999966621398926,
                    "class_id": 1,
                    "class": "top"
                }
            ]
        },
        {
            "class": "DiningTable",
            "confidence": 0.9371365308761597,
            "x": 462.88739013671875,
            "y": 244.0244140625,
            "width": 58.286895751953125,
            "height": 101.35101318359375,
            "keypoints": [
                {
                    "x": 463.0405578613281,
                    "y": 243.73660278320312,
                    "confidence": 0.9999550580978394,
                    "class_id": 0,
                    "class": "keypoint_0"
                },
                {
                    "x": 0.0,
                    "y": 0.0,
                    "confidence": 4.060754508827813e-05,
                    "class_id": 1,
                    "class": "keypoint_1"
                }
            ]
        },
        {
            "class": "door",
            "confidence": 0.9236390590667725,
            "x": 557.2498168945312,
            "y": 241.909423828125,
            "width": 25.6978759765625,
            "height": 35.1925048828125,
            "keypoints": [
                {
                    "x": 546.182373046875,
                    "y": 259.6761474609375,
                    "confidence": 0.9999542236328125,
                    "class_id": 0,
                    "class": "bottom"
                },
                {
                    "x": 546.380615234375,
                    "y": 224.3125762939453,
                    "confidence": 0.999996542930603,
                    "class_id": 1,
                    "class": "top"
                }
            ]
        },
        {
            "class": "door",
            "confidence": 0.920778214931488,
            "x": 524.84716796875,
            "y": 365.7585144042969,
            "width": 28.55999755859375,
            "height": 36.012939453125,
            "keypoints": [
                {
                    "x": 537.76123046875,
                    "y": 349.0150451660156,
                    "confidence": 0.9999755620956421,
                    "class_id": 0,
                    "class": "bottom"
                },
                {
                    "x": 511.10772705078125,
                    "y": 348.63372802734375,
                    "confidence": 0.9999209642410278,
                    "class_id": 1,
                    "class": "top"
                }
            ]
        },
        {
            "class": "door",
            "confidence": 0.9173591136932373,
            "x": 619.2825317382812,
            "y": 55.667884826660156,
            "width": 20.9017333984375,
            "height": 28.415233612060547,
            "keypoints": [
                {
                    "x": 608.4118041992188,
                    "y": 68.0005111694336,
                    "confidence": 0.9999904632568359,
                    "class_id": 0,
                    "class": "bottom"
                },
                {
                    "x": 609.765625,
                    "y": 43.16815948486328,
                    "confidence": 0.9999969005584717,
                    "class_id": 1,
                    "class": "top"
                }
            ]
        },
        {
            "class": "LargeSofa",
            "confidence": 0.9160259962081909,
            "x": 354.20391845703125,
            "y": 173.23196411132812,
            "width": 72.50393676757812,
            "height": 26.999176025390625,
            "keypoints": [
                {
                    "x": 354.9291076660156,
                    "y": 185.83726501464844,
                    "confidence": 0.9999932050704956,
                    "class_id": 0,
                    "class": "bottom"
                },
                {
                    "x": 355.06658935546875,
                    "y": 160.06204223632812,
                    "confidence": 0.9999986886978149,
                    "class_id": 1,
                    "class": "top"
                }
            ]
        },
        {
            "class": "door",
            "confidence": 0.9093290567398071,
            "x": 160.33123779296875,
            "y": 207.6025848388672,
            "width": 22.915298461914062,
            "height": 27.537750244140625,
            "keypoints": [
                {
                    "x": 171.25306701660156,
                    "y": 217.57427978515625,
                    "confidence": 0.999617338180542,
                    "class_id": 0,
                    "class": "bottom"
                },
                {
                    "x": 150.13760375976562,
                    "y": 217.1051025390625,
                    "confidence": 0.9999581575393677,
                    "class_id": 1,
                    "class": "top"
                }
            ]
        },
        {
            "class": "door",
            "confidence": 0.9065916538238525,
            "x": 526.158203125,
            "y": 205.84234619140625,
            "width": 28.3763427734375,
            "height": 35.958587646484375,
            "keypoints": [
                {
                    "x": 540.34326171875,
                    "y": 225.0211181640625,
                    "confidence": 0.9999585151672363,
                    "class_id": 0,
                    "class": "bottom"
                },
                {
                    "x": 512.392822265625,
                    "y": 224.30624389648438,
                    "confidence": 0.9999961853027344,
                    "class_id": 1,
                    "class": "top"
                }
            ]
        },
        {
            "class": "door",
            "confidence": 0.8988435864448547,
            "x": 649.7142333984375,
            "y": 209.68557739257812,
            "width": 22.1060791015625,
            "height": 27.075546264648438,
            "keypoints": [
                {
                    "x": 659.9300537109375,
                    "y": 221.32398986816406,
                    "confidence": 0.9999825954437256,
                    "class_id": 0,
                    "class": "bottom"
                },
                {
                    "x": 640.0745849609375,
                    "y": 222.71791076660156,
                    "confidence": 0.9999938011169434,
                    "class_id": 1,
                    "class": "top"
                }
            ]
        },
        {
            "class": "door",
            "confidence": 0.8969131708145142,
            "x": 206.75799560546875,
            "y": 407.47882080078125,
            "width": 29.753768920898438,
            "height": 44.50018310546875,
            "keypoints": [
                {
                    "x": 194.47669982910156,
                    "y": 385.8482360839844,
                    "confidence": 0.9999927282333374,
                    "class_id": 0,
                    "class": "bottom"
                },
                {
                    "x": 193.44554138183594,
                    "y": 427.85784912109375,
                    "confidence": 0.9999991655349731,
                    "class_id": 1,
                    "class": "top"
                }
            ]
        },
        {
            "class": "door",
            "confidence": 0.8945040702819824,
            "x": 184.66888427734375,
            "y": 330.9434814453125,
            "width": 27.352279663085938,
            "height": 37.826812744140625,
            "keypoints": [
                {
                    "x": 197.6939697265625,
                    "y": 312.509033203125,
                    "confidence": 0.9999711513519287,
                    "class_id": 0,
                    "class": "bottom"
                },
                {
                    "x": 197.1524658203125,
                    "y": 346.75323486328125,
                    "confidence": 0.9999951124191284,
                    "class_id": 1,
                    "class": "top"
                }
            ]
        },
        {
            "class": "door",
            "confidence": 0.8861435651779175,
            "x": 443.60040283203125,
            "y": 495.8126220703125,
            "width": 23.81329345703125,
            "height": 30.851043701171875,
            "keypoints": [
                {
                    "x": 432.1156005859375,
                    "y": 481.4892272949219,
                    "confidence": 0.9999151229858398,
                    "class_id": 0,
                    "class": "bottom"
                },
                {
                    "x": 453.5439147949219,
                    "y": 481.26666259765625,
                    "confidence": 0.999848484992981,
                    "class_id": 1,
                    "class": "top"
                }
            ]
        },
        {
            "class": "LargeSofa",
            "confidence": 0.8840981721878052,
            "x": 311.24249267578125,
            "y": 231.17776489257812,
            "width": 19.810150146484375,
            "height": 92.630615234375,
            "keypoints": [
                {
                    "x": 320.1932373046875,
                    "y": 224.88111877441406,
                    "confidence": 0.9999189376831055,
                    "class_id": 0,
                    "class": "bottom"
                },
                {
                    "x": 302.1471252441406,
                    "y": 224.18075561523438,
                    "confidence": 0.9999654293060303,
                    "class_id": 1,
                    "class": "top"
                }
            ]
        },
        {
            "class": "LargeSofa",
            "confidence": 0.8753398656845093,
            "x": 252.62887573242188,
            "y": 109.04631042480469,
            "width": 68.1224365234375,
            "height": 26.796615600585938,
            "keypoints": [
                {
                    "x": 251.65968322753906,
                    "y": 121.05622863769531,
                    "confidence": 0.999988317489624,
                    "class_id": 0,
                    "class": "bottom"
                },
                {
                    "x": 251.6521759033203,
                    "y": 97.66856384277344,
                    "confidence": 0.9999926090240479,
                    "class_id": 1,
                    "class": "top"
                }
            ]
        },
        {
            "class": "door",
            "confidence": 0.8737264275550842,
            "x": 361.78533935546875,
            "y": 398.39794921875,
            "width": 19.7999267578125,
            "height": 27.234161376953125,
            "keypoints": [
                {
                    "x": 371.5033264160156,
                    "y": 385.8802185058594,
                    "confidence": 0.9999860525131226,
                    "class_id": 0,
                    "class": "bottom"
                },
                {
                    "x": 372.13702392578125,
                    "y": 409.9044494628906,
                    "confidence": 0.9999955892562866,
                    "class_id": 1,
                    "class": "top"
                }
            ]
        },
        {
            "class": "sink",
            "confidence": 0.869983971118927,
            "x": 420.78240966796875,
            "y": 471.2762451171875,
            "width": 20.4254150390625,
            "height": 16.023101806640625,
            "keypoints": [
                {
                    "x": 421.069580078125,
                    "y": 471.13397216796875,
                    "confidence": 0.9999587535858154,
                    "class_id": 0,
                    "class": "keypoint_0"
                },
                {
                    "x": 0.0,
                    "y": 0.0,
                    "confidence": 0.00011778929183492437,
                    "class_id": 1,
                    "class": "keypoint_1"
                }
            ]
        },
        {
            "class": "door",
            "confidence": 0.8692058324813843,
            "x": 338.4091491699219,
            "y": 474.88140869140625,
            "width": 18.81060791015625,
            "height": 25.17291259765625,
            "keypoints": [
                {
                    "x": 329.3970947265625,
                    "y": 485.6503601074219,
                    "confidence": 0.9999877214431763,
                    "class_id": 0,
                    "class": "bottom"
                },
                {
                    "x": 330.00152587890625,
                    "y": 463.9640197753906,
                    "confidence": 0.9999902248382568,
                    "class_id": 1,
                    "class": "top"
                }
            ]
        },
        {
            "class": "door",
            "confidence": 0.8655810952186584,
            "x": 552.345703125,
            "y": 490.2376708984375,
            "width": 23.15191650390625,
            "height": 28.33197021484375,
            "keypoints": [
                {
                    "x": 562.6082153320312,
                    "y": 477.9278564453125,
                    "confidence": 0.9999681711196899,
                    "class_id": 0,
                    "class": "bottom"
                },
                {
                    "x": 543.5259399414062,
                    "y": 477.01751708984375,
                    "confidence": 0.9999701976776123,
                    "class_id": 1,
                    "class": "top"
                }
            ]
        },
        {
            "class": "tv",
            "confidence": 0.8483608365058899,
            "x": 516.3705444335938,
            "y": 123.59788513183594,
            "width": 10.324249267578125,
            "height": 110.8237533569336,
            "keypoints": [
                {
                    "x": 517.189208984375,
                    "y": 103.45609283447266,
                    "confidence": 0.9994447827339172,
                    "class_id": 0,
                    "class": "keypoint_0"
                },
                {
                    "x": 0.0,
                    "y": 0.0,
                    "confidence": 0.00023411215806845576,
                    "class_id": 1,
                    "class": "keypoint_1"
                }
            ]
        },
        {
            "class": "wall",
            "confidence": 0.8481905460357666,
            "x": 652.1788330078125,
            "y": 9.378259658813477,
            "width": 88.611083984375,
            "height": 6.22680139541626,
            "keypoints": [
                {
                    "x": 651.1458740234375,
                    "y": 9.599980354309082,
                    "confidence": 0.9962188601493835,
                    "class_id": 0,
                    "class": "keypoint_0"
                },
                {
                    "x": 0.0,
                    "y": 0.0,
                    "confidence": 0.0027869599871337414,
                    "class_id": 1,
                    "class": "keypoint_1"
                }
            ]
        },
        {
            "class": "wall",
            "confidence": 0.8406919240951538,
            "x": 367.468017578125,
            "y": 366.856201171875,
            "width": 7.53076171875,
            "height": 37.648712158203125,
            "keypoints": [
                {
                    "x": 367.70648193359375,
                    "y": 366.9024353027344,
                    "confidence": 0.9997820258140564,
                    "class_id": 0,
                    "class": "keypoint_0"
                },
                {
                    "x": 0.0,
                    "y": 0.0,
                    "confidence": 0.00023137274547480047,
                    "class_id": 1,
                    "class": "keypoint_1"
                }
            ]
        },
        {
            "class": "tv",
            "confidence": 0.8305291533470154,
            "x": 609.2255859375,
            "y": 341.96148681640625,
            "width": 51.52532958984375,
            "height": 12.099945068359375,
            "keypoints": [
                {
                    "x": 609.6511840820312,
                    "y": 340.00836181640625,
                    "confidence": 0.9999428987503052,
                    "class_id": 0,
                    "class": "keypoint_0"
                },
                {
                    "x": 0.0,
                    "y": 0.0,
                    "confidence": 0.00021452497458085418,
                    "class_id": 1,
                    "class": "keypoint_1"
                }
            ]
        },
        {
            "class": "tv",
            "confidence": 0.8256667852401733,
            "x": 592.4349365234375,
            "y": 470.3388977050781,
            "width": 53.03900146484375,
            "height": 12.92108154296875,
            "keypoints": [
                {
                    "x": 592.311767578125,
                    "y": 469.19793701171875,
                    "confidence": 0.9998632669448853,
                    "class_id": 0,
                    "class": "keypoint_0"
                },
                {
                    "x": 0.0,
                    "y": 0.0,
                    "confidence": 0.00041328099905513227,
                    "class_id": 1,
                    "class": "keypoint_1"
                }
            ]
        },
        {
            "class": "wall",
            "confidence": 0.8250768780708313,
            "x": 523.0523071289062,
            "y": 478.9918212890625,
            "width": 36.5423583984375,
            "height": 5.818389892578125,
            "keypoints": [
                {
                    "x": 522.037841796875,
                    "y": 478.9573974609375,
                    "confidence": 0.9997768998146057,
                    "class_id": 0,
                    "class": "keypoint_0"
                },
                {
                    "x": 0.0,
                    "y": 0.0,
                    "confidence": 0.0003477382706478238,
                    "class_id": 1,
                    "class": "keypoint_1"
                }
            ]
        },
        {
            "class": "wall",
            "confidence": 0.8243001103401184,
            "x": 651.7785034179688,
            "y": 154.92869567871094,
            "width": 83.9375,
            "height": 3.8529052734375,
            "keypoints": [
                {
                    "x": 651.0889282226562,
                    "y": 154.6211700439453,
                    "confidence": 0.9977606534957886,
                    "class_id": 0,
                    "class": "keypoint_0"
                },
                {
                    "x": 0.0,
                    "y": 0.0,
                    "confidence": 0.0020702898036688566,
                    "class_id": 1,
                    "class": "keypoint_1"
                }
            ]
        },
        {
            "class": "wall",
            "confidence": 0.8192011713981628,
            "x": 341.001953125,
            "y": 514.0731811523438,
            "width": 25.35760498046875,
            "height": 5.562957763671875,
            "keypoints": [
                {
                    "x": 340.9243469238281,
                    "y": 514.4629516601562,
                    "confidence": 0.9995974898338318,
                    "class_id": 0,
                    "class": "keypoint_0"
                },
                {
                    "x": 0.0,
                    "y": 0.0,
                    "confidence": 0.0009454978862777352,
                    "class_id": 1,
                    "class": "keypoint_1"
                }
            ]
        },
        {
            "class": "wall",
            "confidence": 0.8176080584526062,
            "x": 420.36029052734375,
            "y": 482.5024719238281,
            "width": 24.1260986328125,
            "height": 3.879638671875,
            "keypoints": [
                {
                    "x": 420.1301574707031,
                    "y": 482.0640869140625,
                    "confidence": 0.9976533055305481,
                    "class_id": 0,
                    "class": "keypoint_0"
                },
                {
                    "x": 0.0,
                    "y": 0.0,
                    "confidence": 0.0022134031169116497,
                    "class_id": 1,
                    "class": "keypoint_1"
                }
            ]
        },
        {
            "class": "wall",
            "confidence": 0.8145416975021362,
            "x": 193.43911743164062,
            "y": 366.8341064453125,
            "width": 8.046096801757812,
            "height": 37.146942138671875,
            "keypoints": [
                {
                    "x": 193.71083068847656,
                    "y": 366.3778076171875,
                    "confidence": 0.9999593496322632,
                    "class_id": 0,
                    "class": "keypoint_0"
                },
                {
                    "x": 0.0,
                    "y": 0.0,
                    "confidence": 2.3342963686445728e-05,
                    "class_id": 1,
                    "class": "keypoint_1"
                }
            ]
        },
        {
            "class": "wardrobe",
            "confidence": 0.8128969669342041,
            "x": 576.991943359375,
            "y": 208.78916931152344,
            "width": 67.00079345703125,
            "height": 20.084930419921875,
            "keypoints": [
                {
                    "x": 581.35546875,
                    "y": 217.46240234375,
                    "confidence": 0.9999725818634033,
                    "class_id": 0,
                    "class": "top"
                },
                {
                    "x": 580.2041015625,
                    "y": 198.77467346191406,
                    "confidence": 0.9996115565299988,
                    "class_id": 1,
                    "class": "bottom"
                }
            ]
        },
        {
            "class": "wall",
            "confidence": 0.8103396892547607,
            "x": 101.34777069091797,
            "y": 289.9847412109375,
            "width": 5.9787750244140625,
            "height": 194.66213989257812,
            "keypoints": [
                {
                    "x": 101.7261962890625,
                    "y": 285.49090576171875,
                    "confidence": 0.9998877048492432,
                    "class_id": 0,
                    "class": "keypoint_0"
                },
                {
                    "x": 0.0,
                    "y": 0.0,
                    "confidence": 0.0001931223669089377,
                    "class_id": 1,
                    "class": "keypoint_1"
                }
            ]
        },
        {
            "class": "window",
            "confidence": 0.8093776106834412,
            "x": 361.7418518066406,
            "y": 514.5089111328125,
            "width": 16.40679931640625,
            "height": 5.270782470703125,
            "keypoints": [
                {
                    "x": 362.7684631347656,
                    "y": 514.6475219726562,
                    "confidence": 0.9994021654129028,
                    "class_id": 0,
                    "class": "keypoint_0"
                },
                {
                    "x": 0.0,
                    "y": 0.0,
                    "confidence": 0.002150650369003415,
                    "class_id": 1,
                    "class": "keypoint_1"
                }
            ]
        },
        {
            "class": "wall",
            "confidence": 0.8068743348121643,
            "x": 582.65087890625,
            "y": 545.7828369140625,
            "width": 149.67120361328125,
            "height": 7.70294189453125,
            "keypoints": [
                {
                    "x": 580.9404296875,
                    "y": 545.9628295898438,
                    "confidence": 0.9987325072288513,
                    "class_id": 0,
                    "class": "keypoint_0"
                },
                {
                    "x": 0.0,
                    "y": 0.0,
                    "confidence": 0.000851900374982506,
                    "class_id": 1,
                    "class": "keypoint_1"
                }
            ]
        },
        {
            "class": "wall",
            "confidence": 0.8032212853431702,
            "x": 697.275634765625,
            "y": 37.956878662109375,
            "width": 19.2474365234375,
            "height": 7.297100067138672,
            "keypoints": [
                {
                    "x": 696.1100463867188,
                    "y": 38.683250427246094,
                    "confidence": 0.999794065952301,
                    "class_id": 0,
                    "class": "keypoint_0"
                },
                {
                    "x": 0.0,
                    "y": 0.0,
                    "confidence": 0.00038864067755639553,
                    "class_id": 1,
                    "class": "keypoint_1"
                }
            ]
        },
        {
            "class": "wall",
            "confidence": 0.7996952533721924,
            "x": 470.73193359375,
            "y": 350.4316101074219,
            "width": 31.683013916015625,
            "height": 5.39453125,
            "keypoints": [
                {
                    "x": 470.4967041015625,
                    "y": 350.373046875,
                    "confidence": 0.9999380111694336,
                    "class_id": 0,
                    "class": "keypoint_0"
                },
                {
                    "x": 0.0,
                    "y": 0.0,
                    "confidence": 0.00011321385682094842,
                    "class_id": 1,
                    "class": "keypoint_1"
                }
            ]
        },
        {
            "class": "wall",
            "confidence": 0.7955589890480042,
            "x": 148.24209594726562,
            "y": 380.72650146484375,
            "width": 98.81993865966797,
            "height": 8.397674560546875,
            "keypoints": [
                {
                    "x": 149.0609893798828,
                    "y": 380.61932373046875,
                    "confidence": 0.9996650218963623,
                    "class_id": 0,
                    "class": "keypoint_0"
                },
                {
                    "x": 0.0,
                    "y": 0.0,
                    "confidence": 0.0003132091951556504,
                    "class_id": 1,
                    "class": "keypoint_1"
                }
            ]
        },
        {
            "class": "sink",
            "confidence": 0.7914156913757324,
            "x": 461.252685546875,
            "y": 418.5114440917969,
            "width": 14.953399658203125,
            "height": 23.79107666015625,
            "keypoints": [
                {
                    "x": 461.4161376953125,
                    "y": 419.12738037109375,
                    "confidence": 0.9986836314201355,
                    "class_id": 0,
                    "class": "keypoint_0"
                },
                {
                    "x": 0.0,
                    "y": 0.0,
                    "confidence": 0.0032123331911861897,
                    "class_id": 1,
                    "class": "keypoint_1"
                }
            ]
        },
        {
            "class": "wall",
            "confidence": 0.789354145526886,
            "x": 283.1644592285156,
            "y": 434.8515625,
            "width": 179.1110076904297,
            "height": 4.59039306640625,
            "keypoints": [
                {
                    "x": 287.9153137207031,
                    "y": 434.6429443359375,
                    "confidence": 0.999840259552002,
                    "class_id": 0,
                    "class": "keypoint_0"
                },
                {
                    "x": 0.0,
                    "y": 0.0,
                    "confidence": 0.00020989809127058834,
                    "class_id": 1,
                    "class": "keypoint_1"
                }
            ]
        },
        {
            "class": "wall",
            "confidence": 0.7844668030738831,
            "x": 684.438232421875,
            "y": 223.528076171875,
            "width": 17.17999267578125,
            "height": 7.2002410888671875,
            "keypoints": [
                {
                    "x": 683.8641357421875,
                    "y": 222.77264404296875,
                    "confidence": 0.9984012246131897,
                    "class_id": 0,
                    "class": "keypoint_0"
                },
                {
                    "x": 0.0,
                    "y": 0.0,
                    "confidence": 0.0005359263741411269,
                    "class_id": 1,
                    "class": "keypoint_1"
                }
            ]
        },
        {
            "class": "WashBasin",
            "confidence": 0.7831279635429382,
            "x": 681.9295654296875,
            "y": 203.9320068359375,
            "width": 15.0543212890625,
            "height": 15.271347045898438,
            "keypoints": [
                {
                    "x": 674.1614379882812,
                    "y": 203.79934692382812,
                    "confidence": 0.9998947381973267,
                    "class_id": 0,
                    "class": "bottom"
                },
                {
                    "x": 687.7099609375,
                    "y": 203.81336975097656,
                    "confidence": 0.9997039437294006,
                    "class_id": 1,
                    "class": "top"
                }
            ]
        },
        {
            "class": "wall",
            "confidence": 0.7754979729652405,
            "x": 610.196044921875,
            "y": 478.8648681640625,
            "width": 96.58160400390625,
            "height": 4.316986083984375,
            "keypoints": [
                {
                    "x": 606.1555786132812,
                    "y": 478.5050048828125,
                    "confidence": 0.999894380569458,
                    "class_id": 0,
                    "class": "keypoint_0"
                },
                {
                    "x": 0.0,
                    "y": 0.0,
                    "confidence": 8.478420204482973e-05,
                    "class_id": 1,
                    "class": "keypoint_1"
                }
            ]
        },
        {
            "class": "door",
            "confidence": 0.7727732062339783,
            "x": 495.0811767578125,
            "y": 363.14508056640625,
            "width": 20.498809814453125,
            "height": 29.704193115234375,
            "keypoints": [
                {
                    "x": 484.6130065917969,
                    "y": 348.98974609375,
                    "confidence": 0.9999161958694458,
                    "class_id": 0,
                    "class": "bottom"
                },
                {
                    "x": 503.11383056640625,
                    "y": 347.5661315917969,
                    "confidence": 0.9996013045310974,
                    "class_id": 1,
                    "class": "top"
                }
            ]
        },
        {
            "class": "wall",
            "confidence": 0.7677443623542786,
            "x": 667.896728515625,
            "y": 352.76739501953125,
            "width": 54.54901123046875,
            "height": 7.761932373046875,
            "keypoints": [
                {
                    "x": 666.0785522460938,
                    "y": 352.9767761230469,
                    "confidence": 0.9996464252471924,
                    "class_id": 0,
                    "class": "keypoint_0"
                },
                {
                    "x": 0.0,
                    "y": 0.0,
                    "confidence": 0.0001222476566908881,
                    "class_id": 1,
                    "class": "keypoint_1"
                }
            ]
        },
        {
            "class": "wall",
            "confidence": 0.766815185546875,
            "x": 351.2250061035156,
            "y": 563.6844482421875,
            "width": 6.114013671875,
            "height": 42.889404296875,
            "keypoints": [
                {
                    "x": 351.55072021484375,
                    "y": 563.9436645507812,
                    "confidence": 0.999845027923584,
                    "class_id": 0,
                    "class": "keypoint_0"
                },
                {
                    "x": 0.0,
                    "y": 0.0,
                    "confidence": 4.1428018448641524e-05,
                    "class_id": 1,
                    "class": "keypoint_1"
                }
            ]
        },
        {
            "class": "wall",
            "confidence": 0.7473149299621582,
            "x": 184.18856811523438,
            "y": 109.39601135253906,
            "width": 23.551971435546875,
            "height": 6.298622131347656,
            "keypoints": [
                {
                    "x": 184.4560089111328,
                    "y": 109.47761535644531,
                    "confidence": 0.9998939037322998,
                    "class_id": 0,
                    "class": "keypoint_0"
                },
                {
                    "x": 0.0,
                    "y": 0.0,
                    "confidence": 0.00022287934552878141,
                    "class_id": 1,
                    "class": "keypoint_1"
                }
            ]
        },
        {
            "class": "wall",
            "confidence": 0.7458311319351196,
            "x": 330.8695068359375,
            "y": 448.82720947265625,
            "width": 4.159820556640625,
            "height": 29.418304443359375,
            "keypoints": [
                {
                    "x": 330.6207580566406,
                    "y": 447.8909606933594,
                    "confidence": 0.999742329120636,
                    "class_id": 0,
                    "class": "keypoint_0"
                },
                {
                    "x": 0.0,
                    "y": 0.0,
                    "confidence": 0.00021944832406006753,
                    "class_id": 1,
                    "class": "keypoint_1"
                }
            ]
        },
        {
            "class": "wall",
            "confidence": 0.7345044612884521,
            "x": 241.7034912109375,
            "y": 509.14117431640625,
            "width": 20.600814819335938,
            "height": 3.855804443359375,
            "keypoints": [
                {
                    "x": 242.01388549804688,
                    "y": 509.3118591308594,
                    "confidence": 0.9984536170959473,
                    "class_id": 0,
                    "class": "keypoint_0"
                },
                {
                    "x": 0.0,
                    "y": 0.0,
                    "confidence": 0.0020685370545834303,
                    "class_id": 1,
                    "class": "keypoint_1"
                }
            ]
        },
        {
            "class": "wall",
            "confidence": 0.7321170568466187,
            "x": 668.4021606445312,
            "y": 90.29617309570312,
            "width": 50.4656982421875,
            "height": 4.41448974609375,
            "keypoints": [
                {
                    "x": 666.7110595703125,
                    "y": 90.37693786621094,
                    "confidence": 0.9991624355316162,
                    "class_id": 0,
                    "class": "keypoint_0"
                },
                {
                    "x": 0.0,
                    "y": 0.0,
                    "confidence": 0.0008202763856388628,
                    "class_id": 1,
                    "class": "keypoint_1"
                }
            ]
        },
        {
            "class": "wardrobe",
            "confidence": 0.7194475531578064,
            "x": 518.9696655273438,
            "y": 429.94329833984375,
            "width": 16.2923583984375,
            "height": 84.53701782226562,
            "keypoints": [
                {
                    "x": 513.9065551757812,
                    "y": 426.6889343261719,
                    "confidence": 0.9986633062362671,
                    "class_id": 0,
                    "class": "top"
                },
                {
                    "x": 522.3038940429688,
                    "y": 427.28643798828125,
                    "confidence": 0.9828604459762573,
                    "class_id": 1,
                    "class": "bottom"
                }
            ]
        },
        {
            "class": "wall",
            "confidence": 0.7112746238708496,
            "x": 462.26788330078125,
            "y": 482.3609619140625,
            "width": 16.99066162109375,
            "height": 4.862274169921875,
            "keypoints": [
                {
                    "x": 462.4554443359375,
                    "y": 482.0845947265625,
                    "confidence": 0.9965907335281372,
                    "class_id": 0,
                    "class": "keypoint_0"
                },
                {
                    "x": 0.0,
                    "y": 0.0,
                    "confidence": 0.002688455628231168,
                    "class_id": 1,
                    "class": "keypoint_1"
                }
            ]
        },
        {
            "class": "wall",
            "confidence": 0.7070952653884888,
            "x": 364.64532470703125,
            "y": 349.946533203125,
            "width": 135.54922485351562,
            "height": 4.2115478515625,
            "keypoints": [
                {
                    "x": 364.3061828613281,
                    "y": 350.03564453125,
                    "confidence": 0.9999347925186157,
                    "class_id": 0,
                    "class": "keypoint_0"
                },
                {
                    "x": 0.0,
                    "y": 0.0,
                    "confidence": 4.061401341459714e-05,
                    "class_id": 1,
                    "class": "keypoint_1"
                }
            ]
        },
        {
            "class": "ToiletSeat",
            "confidence": 0.7063302397727966,
            "x": 360.17156982421875,
            "y": 500.31646728515625,
            "width": 14.981781005859375,
            "height": 19.908294677734375,
            "keypoints": [
                {
                    "x": 358.83349609375,
                    "y": 491.8508605957031,
                    "confidence": 0.9992114305496216,
                    "class_id": 0,
                    "class": "bottom"
                },
                {
                    "x": 357.99298095703125,
                    "y": 507.1197204589844,
                    "confidence": 0.9988692402839661,
                    "class_id": 1,
                    "class": "top"
                }
            ]
        },
        {
            "class": "wall",
            "confidence": 0.7043234705924988,
            "x": 608.1448974609375,
            "y": 480.1689758300781,
            "width": 99.28167724609375,
            "height": 6.61260986328125,
            "keypoints": [
                {
                    "x": 605.6302490234375,
                    "y": 480.1905212402344,
                    "confidence": 0.9997294545173645,
                    "class_id": 0,
                    "class": "keypoint_0"
                },
                {
                    "x": 0.0,
                    "y": 0.0,
                    "confidence": 3.735236532520503e-05,
                    "class_id": 1,
                    "class": "keypoint_1"
                }
            ]
        },
        {
            "class": "window",
            "confidence": 0.7026416063308716,
            "x": 297.8039855957031,
            "y": 123.00285339355469,
            "width": 6.82135009765625,
            "height": 58.85474395751953,
            "keypoints": [
                {
                    "x": 297.30535888671875,
                    "y": 123.29190063476562,
                    "confidence": 0.9997877478599548,
                    "class_id": 0,
                    "class": "keypoint_0"
                },
                {
                    "x": 0.0,
                    "y": 0.0,
                    "confidence": 0.0004794839187525213,
                    "class_id": 1,
                    "class": "keypoint_1"
                }
            ]
        },
        {
            "class": "wall",
            "confidence": 0.6980797052383423,
            "x": 374.567138671875,
            "y": 514.9107666015625,
            "width": 11.0452880859375,
            "height": 4.345703125,
            "keypoints": [
                {
                    "x": 374.0289611816406,
                    "y": 514.8466186523438,
                    "confidence": 0.9994598031044006,
                    "class_id": 0,
                    "class": "keypoint_0"
                },
                {
                    "x": 0.0,
                    "y": 0.0,
                    "confidence": 0.0013580563245341182,
                    "class_id": 1,
                    "class": "keypoint_1"
                }
            ]
        },
        {
            "class": "wall",
            "confidence": 0.6964182257652283,
            "x": 296.84295654296875,
            "y": 392.31787109375,
            "width": 4.1502685546875,
            "height": 87.10055541992188,
            "keypoints": [
                {
                    "x": 296.4820861816406,
                    "y": 391.948486328125,
                    "confidence": 0.9997088313102722,
                    "class_id": 0,
                    "class": "keypoint_0"
                },
                {
                    "x": 0.0,
                    "y": 0.0,
                    "confidence": 0.00024349668819922954,
                    "class_id": 1,
                    "class": "keypoint_1"
                }
            ]
        },
        {
            "class": "wall",
            "confidence": 0.6961843967437744,
            "x": 184.00991821289062,
            "y": 218.80181884765625,
            "width": 26.462936401367188,
            "height": 4.9898223876953125,
            "keypoints": [
                {
                    "x": 184.36798095703125,
                    "y": 219.14759826660156,
                    "confidence": 0.9996167421340942,
                    "class_id": 0,
                    "class": "keypoint_0"
                },
                {
                    "x": 0.0,
                    "y": 0.0,
                    "confidence": 0.0004880797059740871,
                    "class_id": 1,
                    "class": "keypoint_1"
                }
            ]
        },
        {
            "class": "door",
            "confidence": 0.6958204507827759,
            "x": 266.275634765625,
            "y": 363.7985534667969,
            "width": 26.230682373046875,
            "height": 33.53369140625,
            "keypoints": [
                {
                    "x": 279.41326904296875,
                    "y": 348.8003845214844,
                    "confidence": 0.9985435009002686,
                    "class_id": 0,
                    "class": "bottom"
                },
                {
                    "x": 255.75967407226562,
                    "y": 347.8907470703125,
                    "confidence": 0.9897704124450684,
                    "class_id": 1,
                    "class": "top"
                }
            ]
        },
        {
            "class": "wall",
            "confidence": 0.6912667155265808,
            "x": 251.65341186523438,
            "y": 473.716552734375,
            "width": 4.367523193359375,
            "height": 73.73037719726562,
            "keypoints": [
                {
                    "x": 251.64886474609375,
                    "y": 474.0618591308594,
                    "confidence": 0.9997989535331726,
                    "class_id": 0,
                    "class": "keypoint_0"
                },
                {
                    "x": 0.0,
                    "y": 0.0,
                    "confidence": 0.0001950821024365723,
                    "class_id": 1,
                    "class": "keypoint_1"
                }
            ]
        },
        {
            "class": "wall",
            "confidence": 0.6881293654441833,
            "x": 272.552001953125,
            "y": 545.658447265625,
            "width": 166.05506896972656,
            "height": 7.9669189453125,
            "keypoints": [
                {
                    "x": 276.9999694824219,
                    "y": 545.4041748046875,
                    "confidence": 0.9992368221282959,
                    "class_id": 0,
                    "class": "keypoint_0"
                },
                {
                    "x": 0.0,
                    "y": 0.0,
                    "confidence": 0.0002517367829568684,
                    "class_id": 1,
                    "class": "keypoint_1"
                }
            ]
        },
        {
            "class": "door",
            "confidence": 0.6799048185348511,
            "x": 260.58349609375,
            "y": 525.408447265625,
            "width": 24.17254638671875,
            "height": 32.165069580078125,
            "keypoints": [
                {
                    "x": 249.80838012695312,
                    "y": 509.6786804199219,
                    "confidence": 0.999992847442627,
                    "class_id": 0,
                    "class": "bottom"
                },
                {
                    "x": 248.6153106689453,
                    "y": 539.5006103515625,
                    "confidence": 0.9999992847442627,
                    "class_id": 1,
                    "class": "top"
                }
            ]
        },
        {
            "class": "wall",
            "confidence": 0.6796873807907104,
            "x": 341.3174743652344,
            "y": 581.8380737304688,
            "width": 27.8095703125,
            "height": 4.92138671875,
            "keypoints": [
                {
                    "x": 341.78277587890625,
                    "y": 581.5513916015625,
                    "confidence": 0.9985179305076599,
                    "class_id": 0,
                    "class": "keypoint_0"
                },
                {
                    "x": 0.0,
                    "y": 0.0,
                    "confidence": 0.001321505638770759,
                    "class_id": 1,
                    "class": "keypoint_1"
                }
            ]
        },
        {
            "class": "wall",
            "confidence": 0.6780295372009277,
            "x": 298.12811279296875,
            "y": 188.3082275390625,
            "width": 5.646881103515625,
            "height": 72.93246459960938,
            "keypoints": [
                {
                    "x": 297.8446044921875,
                    "y": 187.88633728027344,
                    "confidence": 0.9996194839477539,
                    "class_id": 0,
                    "class": "keypoint_0"
                },
                {
                    "x": 0.0,
                    "y": 0.0,
                    "confidence": 0.00043171830475330353,
                    "class_id": 1,
                    "class": "keypoint_1"
                }
            ]
        },
        {
            "class": "door",
            "confidence": 0.6777575612068176,
            "x": 479.171630859375,
            "y": 497.0863952636719,
            "width": 19.616546630859375,
            "height": 25.4837646484375,
            "keypoints": [
                {
                    "x": 470.5771484375,
                    "y": 508.2032165527344,
                    "confidence": 0.9998639822006226,
                    "class_id": 0,
                    "class": "bottom"
                },
                {
                    "x": 469.9173889160156,
                    "y": 486.0432434082031,
                    "confidence": 0.9996780157089233,
                    "class_id": 1,
                    "class": "top"
                }
            ]
        },
        {
            "class": "wall",
            "confidence": 0.6771292090415955,
            "x": 633.5149536132812,
            "y": 352.95672607421875,
            "width": 122.8787841796875,
            "height": 7.272918701171875,
            "keypoints": [
                {
                    "x": 647.5232543945312,
                    "y": 352.6695556640625,
                    "confidence": 0.9982396364212036,
                    "class_id": 0,
                    "class": "keypoint_0"
                },
                {
                    "x": 0.0,
                    "y": 0.0,
                    "confidence": 0.00015368573076557368,
                    "class_id": 1,
                    "class": "keypoint_1"
                }
            ]
        },
        {
            "class": "wall",
            "confidence": 0.6672660112380981,
            "x": 206.13809204101562,
            "y": 474.40594482421875,
            "width": 5.716705322265625,
            "height": 71.7620849609375,
            "keypoints": [
                {
                    "x": 205.90281677246094,
                    "y": 474.1587829589844,
                    "confidence": 0.9994862079620361,
                    "class_id": 0,
                    "class": "keypoint_0"
                },
                {
                    "x": 0.0,
                    "y": 0.0,
                    "confidence": 0.0007882583886384964,
                    "class_id": 1,
                    "class": "keypoint_1"
                }
            ]
        },
        {
            "class": "wall",
            "confidence": 0.6599082350730896,
            "x": 610.94189453125,
            "y": 143.48565673828125,
            "width": 5.25152587890625,
            "height": 153.1378936767578,
            "keypoints": [
                {
                    "x": 610.8123168945312,
                    "y": 140.1312255859375,
                    "confidence": 0.9999028444290161,
                    "class_id": 0,
                    "class": "keypoint_0"
                },
                {
                    "x": 0.0,
                    "y": 0.0,
                    "confidence": 0.00034826560295186937,
                    "class_id": 1,
                    "class": "keypoint_1"
                }
            ]
        },
        {
            "class": "wall",
            "confidence": 0.6432123780250549,
            "x": 637.0590209960938,
            "y": 479.9871826171875,
            "width": 40.91015625,
            "height": 6.527374267578125,
            "keypoints": [
                {
                    "x": 633.20166015625,
                    "y": 480.2177429199219,
                    "confidence": 0.9952154159545898,
                    "class_id": 0,
                    "class": "keypoint_0"
                },
                {
                    "x": 0.0,
                    "y": 0.0,
                    "confidence": 0.00353649421595037,
                    "class_id": 1,
                    "class": "keypoint_1"
                }
            ]
        },
        {
            "class": "LargeSofa",
            "confidence": 0.6402619481086731,
            "x": 247.65170288085938,
            "y": 269.83111572265625,
            "width": 56.19209289550781,
            "height": 30.403167724609375,
            "keypoints": [
                {
                    "x": 246.60911560058594,
                    "y": 256.65386962890625,
                    "confidence": 0.9998190999031067,
                    "class_id": 0,
                    "class": "bottom"
                },
                {
                    "x": 245.93276977539062,
                    "y": 283.92919921875,
                    "confidence": 0.9990507960319519,
                    "class_id": 1,
                    "class": "top"
                }
            ]
        },
        {
            "class": "wardrobe",
            "confidence": 0.6282299160957336,
            "x": 147.03614807128906,
            "y": 367.11285400390625,
            "width": 88.78105926513672,
            "height": 21.125518798828125,
            "keypoints": [
                {
                    "x": 147.5548095703125,
                    "y": 378.0301818847656,
                    "confidence": 0.9999877214431763,
                    "class_id": 0,
                    "class": "top"
                },
                {
                    "x": 148.49427795410156,
                    "y": 358.1667175292969,
                    "confidence": 0.9999901056289673,
                    "class_id": 1,
                    "class": "bottom"
                }
            ]
        },
        {
            "class": "wall",
            "confidence": 0.6213476657867432,
            "x": 589.8023681640625,
            "y": 221.25621032714844,
            "width": 99.11553955078125,
            "height": 4.35614013671875,
            "keypoints": [
                {
                    "x": 591.2898559570312,
                    "y": 221.21974182128906,
                    "confidence": 0.9984676241874695,
                    "class_id": 0,
                    "class": "keypoint_0"
                },
                {
                    "x": 0.0,
                    "y": 0.0,
                    "confidence": 0.00010678975377231836,
                    "class_id": 1,
                    "class": "keypoint_1"
                }
            ]
        },
        {
            "class": "tv",
            "confidence": 0.6081308722496033,
            "x": 191.02166748046875,
            "y": 278.8100280761719,
            "width": 9.578903198242188,
            "height": 60.70170593261719,
            "keypoints": [
                {
                    "x": 191.21141052246094,
                    "y": 267.4985656738281,
                    "confidence": 0.9993010759353638,
                    "class_id": 0,
                    "class": "keypoint_0"
                },
                {
                    "x": 0.0,
                    "y": 0.0,
                    "confidence": 0.00043978277244605124,
                    "class_id": 1,
                    "class": "keypoint_1"
                }
            ]
        },
        {
            "class": "wall",
            "confidence": 0.5967839360237122,
            "x": 599.8823852539062,
            "y": 350.26129150390625,
            "width": 124.0611572265625,
            "height": 4.551849365234375,
            "keypoints": [
                {
                    "x": 602.206787109375,
                    "y": 350.24664306640625,
                    "confidence": 0.999767005443573,
                    "class_id": 0,
                    "class": "keypoint_0"
                },
                {
                    "x": 0.0,
                    "y": 0.0,
                    "confidence": 2.5307514079031534e-05,
                    "class_id": 1,
                    "class": "keypoint_1"
                }
            ]
        },
        {
            "class": "CenterTable",
            "confidence": 0.586018979549408,
            "x": 351.78814697265625,
            "y": 218.49673461914062,
            "width": 36.376251220703125,
            "height": 29.403884887695312,
            "keypoints": [
                {
                    "x": 352.6448059082031,
                    "y": 218.82913208007812,
                    "confidence": 0.9999344348907471,
                    "class_id": 0,
                    "class": "keypoint_0"
                },
                {
                    "x": 0.0,
                    "y": 0.0,
                    "confidence": 3.1565762128593633e-06,
                    "class_id": 1,
                    "class": "keypoint_1"
                }
            ]
        },
        {
            "class": "wall",
            "confidence": 0.5691921710968018,
            "x": 331.0242004394531,
            "y": 501.32647705078125,
            "width": 3.16424560546875,
            "height": 28.609527587890625,
            "keypoints": [
                {
                    "x": 330.8335876464844,
                    "y": 501.67742919921875,
                    "confidence": 0.9992115497589111,
                    "class_id": 0,
                    "class": "keypoint_0"
                },
                {
                    "x": 0.0,
                    "y": 0.0,
                    "confidence": 0.00057068164460361,
                    "class_id": 1,
                    "class": "keypoint_1"
                }
            ]
        },
        {
            "class": "CenterTable",
            "confidence": 0.5518308877944946,
            "x": 241.33554077148438,
            "y": 225.78067016601562,
            "width": 34.61817932128906,
            "height": 26.405044555664062,
            "keypoints": [
                {
                    "x": 242.50869750976562,
                    "y": 225.60134887695312,
                    "confidence": 0.9999500513076782,
                    "class_id": 0,
                    "class": "keypoint_0"
                },
                {
                    "x": 0.0,
                    "y": 0.0,
                    "confidence": 1.9718701878446154e-05,
                    "class_id": 1,
                    "class": "keypoint_1"
                }
            ]
        },
        {
            "class": "wall",
            "confidence": 0.5398483872413635,
            "x": 610.7213134765625,
            "y": 25.47854232788086,
            "width": 4.18853759765625,
            "height": 33.56169891357422,
            "keypoints": [
                {
                    "x": 610.6336669921875,
                    "y": 25.135787963867188,
                    "confidence": 0.9990139007568359,
                    "class_id": 0,
                    "class": "keypoint_0"
                },
                {
                    "x": 0.0,
                    "y": 0.0,
                    "confidence": 0.0010615662904456258,
                    "class_id": 1,
                    "class": "keypoint_1"
                }
            ]
        },
        {
            "class": "wall",
            "confidence": 0.5256650447845459,
            "x": 599.6888427734375,
            "y": 478.56939697265625,
            "width": 74.6226806640625,
            "height": 3.821624755859375,
            "keypoints": [
                {
                    "x": 605.3801879882812,
                    "y": 479.0894470214844,
                    "confidence": 0.999904990196228,
                    "class_id": 0,
                    "class": "keypoint_0"
                },
                {
                    "x": 0.0,
                    "y": 0.0,
                    "confidence": 9.909431537380442e-05,
                    "class_id": 1,
                    "class": "keypoint_1"
                }
            ]
        },
        {
            "class": "LargeSofa",
            "confidence": 0.5167210698127747,
            "x": 209.61265563964844,
            "y": 167.75933837890625,
            "width": 20.22247314453125,
            "height": 91.76012420654297,
            "keypoints": [
                {
                    "x": 220.071044921875,
                    "y": 166.230224609375,
                    "confidence": 0.9998940229415894,
                    "class_id": 0,
                    "class": "bottom"
                },
                {
                    "x": 201.5806427001953,
                    "y": 166.42909240722656,
                    "confidence": 0.999967098236084,
                    "class_id": 1,
                    "class": "top"
                }
            ]
        },
        {
            "class": "wall",
            "confidence": 0.5147814154624939,
            "x": 370.1576232910156,
            "y": 469.9484558105469,
            "width": 4.452392578125,
            "height": 98.33819580078125,
            "keypoints": [
                {
                    "x": 369.7452087402344,
                    "y": 471.34832763671875,
                    "confidence": 0.999606192111969,
                    "class_id": 0,
                    "class": "keypoint_0"
                },
                {
                    "x": 0.0,
                    "y": 0.0,
                    "confidence": 0.0001748776703607291,
                    "class_id": 1,
                    "class": "keypoint_1"
                }
            ]
        },
        {
            "class": "wall",
            "confidence": 0.5092044472694397,
            "x": 286.71270751953125,
            "y": 436.13165283203125,
            "width": 185.6205596923828,
            "height": 5.964508056640625,
            "keypoints": [
                {
                    "x": 284.32745361328125,
                    "y": 436.4606018066406,
                    "confidence": 0.9997038245201111,
                    "class_id": 0,
                    "class": "keypoint_0"
                },
                {
                    "x": 0.0,
                    "y": 0.0,
                    "confidence": 0.00011896514479303733,
                    "class_id": 1,
                    "class": "keypoint_1"
                }
            ]
        },
        {
            "class": "wardrobe",
            "confidence": 0.5062700510025024,
            "x": 264.25604248046875,
            "y": 468.68035888671875,
            "width": 22.052352905273438,
            "height": 62.805023193359375,
            "keypoints": [
                {
                    "x": 253.1658172607422,
                    "y": 469.4412841796875,
                    "confidence": 0.9989522695541382,
                    "class_id": 0,
                    "class": "top"
                },
                {
                    "x": 275.2168273925781,
                    "y": 468.76605224609375,
                    "confidence": 0.9997645020484924,
                    "class_id": 1,
                    "class": "bottom"
                }
            ]
        },
        {
            "class": "wardrobe",
            "confidence": 0.4842239320278168,
            "x": 554.506103515625,
            "y": 304.1789245605469,
            "width": 16.39154052734375,
            "height": 86.5306396484375,
            "keypoints": [
                {
                    "x": 547.33837890625,
                    "y": 302.33917236328125,
                    "confidence": 0.9997954964637756,
                    "class_id": 0,
                    "class": "top"
                },
                {
                    "x": 562.905029296875,
                    "y": 303.431884765625,
                    "confidence": 0.9920294284820557,
                    "class_id": 1,
                    "class": "bottom"
                }
            ]
        },
        {
            "class": "wall",
            "confidence": 0.4825672209262848,
            "x": 194.4801025390625,
            "y": 434.02197265625,
            "width": 6.2341461181640625,
            "height": 13.3238525390625,
            "keypoints": [
                {
                    "x": 194.83485412597656,
                    "y": 433.22021484375,
                    "confidence": 0.9996362924575806,
                    "class_id": 0,
                    "class": "keypoint_0"
                },
                {
                    "x": 0.0,
                    "y": 0.0,
                    "confidence": 0.0001879002375062555,
                    "class_id": 1,
                    "class": "keypoint_1"
                }
            ]
        },
        {
            "class": "wall",
            "confidence": 0.4795584976673126,
            "x": 614.2357177734375,
            "y": 351.7432556152344,
            "width": 159.01824951171875,
            "height": 5.26593017578125,
            "keypoints": [
                {
                    "x": 601.9359130859375,
                    "y": 351.3885803222656,
                    "confidence": 0.9992265701293945,
                    "class_id": 0,
                    "class": "keypoint_0"
                },
                {
                    "x": 0.0,
                    "y": 0.0,
                    "confidence": 2.1111758542247117e-05,
                    "class_id": 1,
                    "class": "keypoint_1"
                }
            ]
        },
        {
            "class": "WashBasin",
            "confidence": 0.45878270268440247,
            "x": 653.18701171875,
            "y": 165.95230102539062,
            "width": 23.00048828125,
            "height": 15.695053100585938,
            "keypoints": [
                {
                    "x": 657.3993530273438,
                    "y": 172.74749755859375,
                    "confidence": 0.999934196472168,
                    "class_id": 0,
                    "class": "bottom"
                },
                {
                    "x": 657.28369140625,
                    "y": 157.6776885986328,
                    "confidence": 0.9998569488525391,
                    "class_id": 1,
                    "class": "top"
                }
            ]
        },
        {
            "class": "ToiletSeat",
            "confidence": 0.443712443113327,
            "x": 480.69451904296875,
            "y": 387.25384521484375,
            "width": 13.0899658203125,
            "height": 12.563720703125,
            "keypoints": [
                {
                    "x": 485.0588684082031,
                    "y": 387.20416259765625,
                    "confidence": 0.9992585778236389,
                    "class_id": 0,
                    "class": "bottom"
                },
                {
                    "x": 474.6943359375,
                    "y": 387.425537109375,
                    "confidence": 0.9872389435768127,
                    "class_id": 1,
                    "class": "top"
                }
            ]
        },
        {
            "class": "door",
            "confidence": 0.4359925389289856,
            "x": 441.2429504394531,
            "y": 366.20068359375,
            "width": 25.32025146484375,
            "height": 34.645233154296875,
            "keypoints": [
                {
                    "x": 429.3547668457031,
                    "y": 351.0556640625,
                    "confidence": 0.9995843768119812,
                    "class_id": 0,
                    "class": "bottom"
                },
                {
                    "x": 454.560791015625,
                    "y": 349.4343566894531,
                    "confidence": 0.9966345429420471,
                    "class_id": 1,
                    "class": "top"
                }
            ]
        },
        {
            "class": "window",
            "confidence": 0.4244755506515503,
            "x": 412.496826171875,
            "y": 548.54345703125,
            "width": 111.07217407226562,
            "height": 5.58502197265625,
            "keypoints": [
                {
                    "x": 411.1750793457031,
                    "y": 549.3673706054688,
                    "confidence": 0.9997808337211609,
                    "class_id": 0,
                    "class": "keypoint_0"
                },
                {
                    "x": 0.0,
                    "y": 0.0,
                    "confidence": 0.0003480359155219048,
                    "class_id": 1,
                    "class": "keypoint_1"
                }
            ]
        },
        {
            "class": "wall",
            "confidence": 0.42134466767311096,
            "x": 615.1530151367188,
            "y": 350.8979187011719,
            "width": 157.1439208984375,
            "height": 4.23529052734375,
            "keypoints": [
                {
                    "x": 602.1268920898438,
                    "y": 350.2609558105469,
                    "confidence": 0.999832034111023,
                    "class_id": 0,
                    "class": "keypoint_0"
                },
                {
                    "x": 0.0,
                    "y": 0.0,
                    "confidence": 2.769348611764144e-05,
                    "class_id": 1,
                    "class": "keypoint_1"
                }
            ]
        },
        {
            "class": "wall",
            "confidence": 0.4128430485725403,
            "x": 698.064208984375,
            "y": 194.77777099609375,
            "width": 19.1749267578125,
            "height": 6.609893798828125,
            "keypoints": [
                {
                    "x": 697.219970703125,
                    "y": 194.7579345703125,
                    "confidence": 0.9997128844261169,
                    "class_id": 0,
                    "class": "keypoint_0"
                },
                {
                    "x": 0.0,
                    "y": 0.0,
                    "confidence": 0.0005524712614715099,
                    "class_id": 1,
                    "class": "keypoint_1"
                }
            ]
        },
        {
            "class": "wall",
            "confidence": 0.3820829689502716,
            "x": 193.42935180664062,
            "y": 90.59501647949219,
            "width": 6.1753082275390625,
            "height": 44.517860412597656,
            "keypoints": [
                {
                    "x": 193.9249267578125,
                    "y": 90.84181213378906,
                    "confidence": 0.9996812343597412,
                    "class_id": 0,
                    "class": "keypoint_0"
                },
                {
                    "x": 0.0,
                    "y": 0.0,
                    "confidence": 0.0001177699668915011,
                    "class_id": 1,
                    "class": "keypoint_1"
                }
            ]
        },
        {
            "class": "wall",
            "confidence": 0.36268118023872375,
            "x": 196.46832275390625,
            "y": 210.8561248779297,
            "width": 4.7247467041015625,
            "height": 215.86654663085938,
            "keypoints": [
                {
                    "x": 196.58851623535156,
                    "y": 198.06695556640625,
                    "confidence": 0.999657392501831,
                    "class_id": 0,
                    "class": "keypoint_0"
                },
                {
                    "x": 0.0,
                    "y": 0.0,
                    "confidence": 9.014730312628672e-05,
                    "class_id": 1,
                    "class": "keypoint_1"
                }
            ]
        },
        {
            "class": "window",
            "confidence": 0.355223149061203,
            "x": 398.0335998535156,
            "y": 155.46661376953125,
            "width": 194.87200927734375,
            "height": 4.877227783203125,
            "keypoints": [
                {
                    "x": 367.6868591308594,
                    "y": 155.51080322265625,
                    "confidence": 0.9984543323516846,
                    "class_id": 0,
                    "class": "keypoint_0"
                },
                {
                    "x": 0.0,
                    "y": 0.0,
                    "confidence": 0.0011495704529806972,
                    "class_id": 1,
                    "class": "keypoint_1"
                }
            ]
        },
        {
            "class": "ToiletSeat",
            "confidence": 0.3397672772407532,
            "x": 578.314697265625,
            "y": 492.55908203125,
            "width": 16.5001220703125,
            "height": 21.638214111328125,
            "keypoints": [
                {
                    "x": 577.8955078125,
                    "y": 502.3098449707031,
                    "confidence": 0.9999418258666992,
                    "class_id": 0,
                    "class": "bottom"
                },
                {
                    "x": 577.7598266601562,
                    "y": 482.1751708984375,
                    "confidence": 0.9998039603233337,
                    "class_id": 1,
                    "class": "top"
                }
            ]
        },
        {
            "class": "wall",
            "confidence": 0.33865806460380554,
            "x": 330.8426208496094,
            "y": 566.5693969726562,
            "width": 4.5079345703125,
            "height": 36.6741943359375,
            "keypoints": [
                {
                    "x": 331.0522155761719,
                    "y": 566.7305297851562,
                    "confidence": 0.9993983507156372,
                    "class_id": 0,
                    "class": "keypoint_0"
                },
                {
                    "x": 0.0,
                    "y": 0.0,
                    "confidence": 0.0005954563966952264,
                    "class_id": 1,
                    "class": "keypoint_1"
                }
            ]
        },
        {
            "class": "wall",
            "confidence": 0.3166506588459015,
            "x": 147.26559448242188,
            "y": 144.00962829589844,
            "width": 6.0563507080078125,
            "height": 158.03500366210938,
            "keypoints": [
                {
                    "x": 147.6654052734375,
                    "y": 149.189697265625,
                    "confidence": 0.9994701743125916,
                    "class_id": 0,
                    "class": "keypoint_0"
                },
                {
                    "x": 0.0,
                    "y": 0.0,
                    "confidence": 7.541989907622337e-05,
                    "class_id": 1,
                    "class": "keypoint_1"
                }
            ]
        },
        {
            "class": "ToiletSeat",
            "confidence": 0.3115832805633545,
            "x": 578.6297607421875,
            "y": 533.3282470703125,
            "width": 26.7474365234375,
            "height": 17.38739013671875,
            "keypoints": [
                {
                    "x": 578.3090209960938,
                    "y": 524.95068359375,
                    "confidence": 0.999937891960144,
                    "class_id": 0,
                    "class": "bottom"
                },
                {
                    "x": 578.460205078125,
                    "y": 542.8152465820312,
                    "confidence": 0.99909508228302,
                    "class_id": 1,
                    "class": "top"
                }
            ]
        },
        {
            "class": "wall",
            "confidence": 0.2966536283493042,
            "x": 196.95046997070312,
            "y": 191.47763061523438,
            "width": 3.8708648681640625,
            "height": 201.3807373046875,
            "keypoints": [
                {
                    "x": 197.11769104003906,
                    "y": 182.13775634765625,
                    "confidence": 0.9980643391609192,
                    "class_id": 0,
                    "class": "keypoint_0"
                },
                {
                    "x": 0.0,
                    "y": 0.0,
                    "confidence": 0.00185565953142941,
                    "class_id": 1,
                    "class": "keypoint_1"
                }
            ]
        },
        {
            "class": "wall",
            "confidence": 0.2828649878501892,
            "x": 517.139404296875,
            "y": 480.1927490234375,
            "width": 22.117218017578125,
            "height": 7.010162353515625,
            "keypoints": [
                {
                    "x": 518.0405883789062,
                    "y": 479.4382629394531,
                    "confidence": 0.99334716796875,
                    "class_id": 0,
                    "class": "keypoint_0"
                },
                {
                    "x": 0.0,
                    "y": 0.0,
                    "confidence": 0.0019121032673865557,
                    "class_id": 1,
                    "class": "keypoint_1"
                }
            ]
        },
        {
            "class": "window",
            "confidence": 0.27130264043807983,
            "x": 659.353271484375,
            "y": 418.7497253417969,
            "width": 8.96966552734375,
            "height": 118.8099365234375,
            "keypoints": [
                {
                    "x": 658.7258911132812,
                    "y": 419.1943664550781,
                    "confidence": 0.9998819828033447,
                    "class_id": 0,
                    "class": "keypoint_0"
                },
                {
                    "x": 0.0,
                    "y": 0.0,
                    "confidence": 7.128054858185351e-05,
                    "class_id": 1,
                    "class": "keypoint_1"
                }
            ]
        },
        {
            "class": "wall",
            "confidence": 0.2644732594490051,
            "x": 525.4580688476562,
            "y": 511.05462646484375,
            "width": 4.0806884765625,
            "height": 65.32174682617188,
            "keypoints": [
                {
                    "x": 525.939208984375,
                    "y": 510.10546875,
                    "confidence": 0.9980060458183289,
                    "class_id": 0,
                    "class": "keypoint_0"
                },
                {
                    "x": 0.0,
                    "y": 0.0,
                    "confidence": 0.001597602036781609,
                    "class_id": 1,
                    "class": "keypoint_1"
                }
            ]
        },
        {
            "class": "wall",
            "confidence": 0.2614912986755371,
            "x": 620.2484741210938,
            "y": 532.058349609375,
            "width": 5.8077392578125,
            "height": 33.62286376953125,
            "keypoints": [
                {
                    "x": 621.4573974609375,
                    "y": 529.6542358398438,
                    "confidence": 0.9992637038230896,
                    "class_id": 0,
                    "class": "keypoint_0"
                },
                {
                    "x": 0.0,
                    "y": 0.0,
                    "confidence": 0.00016591233725193888,
                    "class_id": 1,
                    "class": "keypoint_1"
                }
            ]
        }
    ]
}