{
    "predictions": [
        {
            "class": "bed",
            "confidence": 0.969499409198761,
            "x": 175.24920654296875,
            "y": 174.9618682861328,
            "width": 75.59552001953125,
            "height": 118.8896484375,
            "keypoints": [
                {
                    "x": 209.46742248535156,
                    "y": 173.5189666748047,
                    "confidence": 0.9999657869338989,
                    "class_id": 0,
                    "class": "bottom"
                },
                {
                    "x": 138.08921813964844,
                    "y": 176.6758270263672,
                    "confidence": 0.9997875094413757,
                    "class_id": 1,
                    "class": "top"
                }
            ]
        },
        {
            "class": "bed",
            "confidence": 0.9670892953872681,
            "x": 175.34011840820312,
            "y": 404.885009765625,
            "width": 76.61882019042969,
            "height": 120.53042602539062,
            "keypoints": [
                {
                    "x": 209.58277893066406,
                    "y": 402.8569641113281,
                    "confidence": 0.999967098236084,
                    "class_id": 0,
                    "class": "bottom"
                },
                {
                    "x": 138.80384826660156,
                    "y": 405.5680236816406,
                    "confidence": 0.9999154806137085,
                    "class_id": 1,
                    "class": "top"
                }
            ]
        },
        {
            "class": "bed",
            "confidence": 0.9636024236679077,
            "x": 295.04962158203125,
            "y": 176.2960205078125,
            "width": 76.16140747070312,
            "height": 121.29246520996094,
            "keypoints": [
                {
                    "x": 329.8819885253906,
                    "y": 179.00881958007812,
                    "confidence": 0.9999611377716064,
                    "class_id": 0,
                    "class": "bottom"
                },
                {
                    "x": 258.0216979980469,
                    "y": 175.89886474609375,
                    "confidence": 0.999931812286377,
                    "class_id": 1,
                    "class": "top"
                }
            ]
        },
        {
            "class": "bed",
            "confidence": 0.9607864022254944,
            "x": 295.9628601074219,
            "y": 400.3888244628906,
            "width": 77.218505859375,
            "height": 119.65496826171875,
            "keypoints": [
                {
                    "x": 330.982177734375,
                    "y": 398.2520446777344,
                    "confidence": 0.9999758005142212,
                    "class_id": 0,
                    "class": "bottom"
                },
                {
                    "x": 260.2026062011719,
                    "y": 399.0893249511719,
                    "confidence": 0.9999814033508301,
                    "class_id": 1,
                    "class": "top"
                }
            ]
        },
        {
            "class": "DiningTable",
            "confidence": 0.9576902389526367,
            "x": 516.5849609375,
            "y": 207.05215454101562,
            "width": 42.43505859375,
            "height": 77.94136047363281,
            "keypoints": [
                {
                    "x": 516.2034301757812,
                    "y": 206.5168914794922,
                    "confidence": 0.9997114539146423,
                    "class_id": 0,
                    "class": "keypoint_0"
                },
                {
                    "x": 0.0,
                    "y": 0.0,
                    "confidence": 8.742025966057554e-05,
                    "class_id": 1,
                    "class": "keypoint_1"
                }
            ]
        },
        {
            "class": "CenterTable",
            "confidence": 0.9562150835990906,
            "x": 495.10595703125,
            "y": 393.0634765625,
            "width": 38.002655029296875,
            "height": 39.142608642578125,
            "keypoints": [
                {
                    "x": 494.5579528808594,
                    "y": 393.20977783203125,
                    "confidence": 0.9998948574066162,
                    "class_id": 0,
                    "class": "keypoint_0"
                },
                {
                    "x": 0.0,
                    "y": 0.0,
                    "confidence": 3.634960012277588e-05,
                    "class_id": 1,
                    "class": "keypoint_1"
                }
            ]
        },
        {
            "class": "LargeSofa",
            "confidence": 0.9541193842887878,
            "x": 455.6817626953125,
            "y": 154.51577758789062,
            "width": 55.241943359375,
            "height": 26.310592651367188,
            "keypoints": [
                {
                    "x": 453.7912292480469,
                    "y": 164.0207061767578,
                    "confidence": 0.9999266862869263,
                    "class_id": 0,
                    "class": "bottom"
                },
                {
                    "x": 454.3303527832031,
                    "y": 145.42889404296875,
                    "confidence": 0.9999511241912842,
                    "class_id": 1,
                    "class": "top"
                }
            ]
        },
        {
            "class": "ArmChair",
            "confidence": 0.9525861740112305,
            "x": 205.82308959960938,
            "y": 274.28436279296875,
            "width": 35.77848815917969,
            "height": 25.5250244140625,
            "keypoints": [
                {
                    "x": 204.38270568847656,
                    "y": 264.6578674316406,
                    "confidence": 0.9999203681945801,
                    "class_id": 0,
                    "class": "bottom"
                },
                {
                    "x": 204.70262145996094,
                    "y": 286.80010986328125,
                    "confidence": 0.999854564666748,
                    "class_id": 1,
                    "class": "top"
                }
            ]
        },
        {
            "class": "wardrobe",
            "confidence": 0.9507054090499878,
            "x": 98.22024536132812,
            "y": 278.241455078125,
            "width": 71.57571411132812,
            "height": 20.232086181640625,
            "keypoints": [
                {
                    "x": 99.67498779296875,
                    "y": 284.82916259765625,
                    "confidence": 0.9999037981033325,
                    "class_id": 0,
                    "class": "top"
                },
                {
                    "x": 99.11019897460938,
                    "y": 270.84979248046875,
                    "confidence": 0.9999299049377441,
                    "class_id": 1,
                    "class": "bottom"
                }
            ]
        },
        {
            "class": "wardrobe",
            "confidence": 0.9502511620521545,
            "x": 291.95672607421875,
            "y": 331.1690673828125,
            "width": 66.83212280273438,
            "height": 17.416656494140625,
            "keypoints": [
                {
                    "x": 292.1604919433594,
                    "y": 324.56884765625,
                    "confidence": 0.9999722242355347,
                    "class_id": 0,
                    "class": "top"
                },
                {
                    "x": 292.8988342285156,
                    "y": 337.697265625,
                    "confidence": 0.9999864101409912,
                    "class_id": 1,
                    "class": "bottom"
                }
            ]
        },
        {
            "class": "wardrobe",
            "confidence": 0.9502284526824951,
            "x": 286.8656005859375,
            "y": 247.284912109375,
            "width": 68.03532409667969,
            "height": 21.3363037109375,
            "keypoints": [
                {
                    "x": 292.3145446777344,
                    "y": 255.34388732910156,
                    "confidence": 0.9998676776885986,
                    "class_id": 0,
                    "class": "top"
                },
                {
                    "x": 292.47857666015625,
                    "y": 239.4493408203125,
                    "confidence": 0.9999284744262695,
                    "class_id": 1,
                    "class": "bottom"
                }
            ]
        },
        {
            "class": "wardrobe",
            "confidence": 0.9490325450897217,
            "x": 98.20238494873047,
            "y": 301.7524719238281,
            "width": 72.05918884277344,
            "height": 21.20989990234375,
            "keypoints": [
                {
                    "x": 99.09444427490234,
                    "y": 292.9946594238281,
                    "confidence": 0.9998530149459839,
                    "class_id": 0,
                    "class": "top"
                },
                {
                    "x": 99.3891372680664,
                    "y": 309.9939270019531,
                    "confidence": 0.9999091625213623,
                    "class_id": 1,
                    "class": "bottom"
                }
            ]
        },
        {
            "class": "LargeSofa",
            "confidence": 0.9487990140914917,
            "x": 489.88128662109375,
            "y": 443.75653076171875,
            "width": 68.71096801757812,
            "height": 27.502716064453125,
            "keypoints": [
                {
                    "x": 490.1098327636719,
                    "y": 431.5704345703125,
                    "confidence": 0.9999791383743286,
                    "class_id": 0,
                    "class": "bottom"
                },
                {
                    "x": 490.439697265625,
                    "y": 455.1507873535156,
                    "confidence": 0.9999923706054688,
                    "class_id": 1,
                    "class": "top"
                }
            ]
        },
        {
            "class": "LargeSofa",
            "confidence": 0.9469478130340576,
            "x": 476.28021240234375,
            "y": 322.3804931640625,
            "width": 34.393585205078125,
            "height": 23.6593017578125,
            "keypoints": [
                {
                    "x": 476.17333984375,
                    "y": 334.09503173828125,
                    "confidence": 0.9995954632759094,
                    "class_id": 0,
                    "class": "bottom"
                },
                {
                    "x": 475.80810546875,
                    "y": 311.1589050292969,
                    "confidence": 0.9998965263366699,
                    "class_id": 1,
                    "class": "top"
                }
            ]
        },
        {
            "class": "LargeSofa",
            "confidence": 0.9449845552444458,
            "x": 443.1134338378906,
            "y": 396.7242431640625,
            "width": 26.50604248046875,
            "height": 67.98233032226562,
            "keypoints": [
                {
                    "x": 455.1318054199219,
                    "y": 394.2865905761719,
                    "confidence": 0.9999499320983887,
                    "class_id": 0,
                    "class": "bottom"
                },
                {
                    "x": 429.6115417480469,
                    "y": 396.0167541503906,
                    "confidence": 0.9998693466186523,
                    "class_id": 1,
                    "class": "top"
                }
            ]
        },
        {
            "class": "WashBasin",
            "confidence": 0.9449083209037781,
            "x": 125.10798645019531,
            "y": 124.52072143554688,
            "width": 21.54224395751953,
            "height": 47.77082061767578,
            "keypoints": [
                {
                    "x": 118.68637084960938,
                    "y": 124.16546630859375,
                    "confidence": 0.9997220635414124,
                    "class_id": 0,
                    "class": "bottom"
                },
                {
                    "x": 130.6409149169922,
                    "y": 122.31869506835938,
                    "confidence": 0.9997380375862122,
                    "class_id": 1,
                    "class": "top"
                }
            ]
        },
        {
            "class": "bed",
            "confidence": 0.9444892406463623,
            "x": 733.6359252929688,
            "y": 195.5213165283203,
            "width": 26.7059326171875,
            "height": 53.627777099609375,
            "keypoints": [
                {
                    "x": 734.1902465820312,
                    "y": 221.05938720703125,
                    "confidence": 0.9999376535415649,
                    "class_id": 0,
                    "class": "bottom"
                },
                {
                    "x": 733.1739501953125,
                    "y": 169.3998565673828,
                    "confidence": 0.9999505281448364,
                    "class_id": 1,
                    "class": "top"
                }
            ]
        },
        {
            "class": "LargeSofa",
            "confidence": 0.9439772963523865,
            "x": 468.3520202636719,
            "y": 481.3041687011719,
            "width": 28.15106201171875,
            "height": 23.75433349609375,
            "keypoints": [
                {
                    "x": 466.9090576171875,
                    "y": 490.1979675292969,
                    "confidence": 0.9999054670333862,
                    "class_id": 0,
                    "class": "bottom"
                },
                {
                    "x": 466.8706359863281,
                    "y": 471.7241516113281,
                    "confidence": 0.9999147653579712,
                    "class_id": 1,
                    "class": "top"
                }
            ]
        },
        {
            "class": "ArmChair",
            "confidence": 0.9433789849281311,
            "x": 163.9843292236328,
            "y": 303.1410217285156,
            "width": 34.49505615234375,
            "height": 27.27410888671875,
            "keypoints": [
                {
                    "x": 163.31265258789062,
                    "y": 315.4898986816406,
                    "confidence": 0.9998793601989746,
                    "class_id": 0,
                    "class": "bottom"
                },
                {
                    "x": 163.20240783691406,
                    "y": 295.0638122558594,
                    "confidence": 0.9999275207519531,
                    "class_id": 1,
                    "class": "top"
                }
            ]
        },
        {
            "class": "LargeSofa",
            "confidence": 0.9415643811225891,
            "x": 439.75927734375,
            "y": 185.0428466796875,
            "width": 23.88555908203125,
            "height": 88.19697570800781,
            "keypoints": [
                {
                    "x": 450.74102783203125,
                    "y": 184.2881317138672,
                    "confidence": 0.9999384880065918,
                    "class_id": 0,
                    "class": "bottom"
                },
                {
                    "x": 429.52301025390625,
                    "y": 185.2650604248047,
                    "confidence": 0.9999079704284668,
                    "class_id": 1,
                    "class": "top"
                }
            ]
        },
        {
            "class": "LargeSofa",
            "confidence": 0.9412651658058167,
            "x": 543.1713256835938,
            "y": 444.8253173828125,
            "width": 35.4228515625,
            "height": 23.411163330078125,
            "keypoints": [
                {
                    "x": 543.0006713867188,
                    "y": 433.90985107421875,
                    "confidence": 0.9998401403427124,
                    "class_id": 0,
                    "class": "bottom"
                },
                {
                    "x": 543.1829833984375,
                    "y": 455.1692199707031,
                    "confidence": 0.9997619986534119,
                    "class_id": 1,
                    "class": "top"
                }
            ]
        },
        {
            "class": "sink",
            "confidence": 0.9408151507377625,
            "x": 624.023193359375,
            "y": 180.01951599121094,
            "width": 19.78759765625,
            "height": 31.40924072265625,
            "keypoints": [
                {
                    "x": 623.8023071289062,
                    "y": 179.54510498046875,
                    "confidence": 0.9994845390319824,
                    "class_id": 0,
                    "class": "keypoint_0"
                },
                {
                    "x": 0.0,
                    "y": 0.0,
                    "confidence": 0.00033040554262697697,
                    "class_id": 1,
                    "class": "keypoint_1"
                }
            ]
        },
        {
            "class": "wardrobe",
            "confidence": 0.9406437277793884,
            "x": 69.237548828125,
            "y": 230.91441345214844,
            "width": 21.063575744628906,
            "height": 112.59689331054688,
            "keypoints": [
                {
                    "x": 59.55900192260742,
                    "y": 224.08135986328125,
                    "confidence": 0.9998706579208374,
                    "class_id": 0,
                    "class": "top"
                },
                {
                    "x": 77.16231536865234,
                    "y": 225.0723114013672,
                    "confidence": 0.9998375177383423,
                    "class_id": 1,
                    "class": "bottom"
                }
            ]
        },
        {
            "class": "ArmChair",
            "confidence": 0.9396378993988037,
            "x": 207.71987915039062,
            "y": 303.814208984375,
            "width": 35.16949462890625,
            "height": 28.50537109375,
            "keypoints": [
                {
                    "x": 205.57859802246094,
                    "y": 317.89251708984375,
                    "confidence": 0.9998612403869629,
                    "class_id": 0,
                    "class": "bottom"
                },
                {
                    "x": 204.91455078125,
                    "y": 295.8177185058594,
                    "confidence": 0.9999672174453735,
                    "class_id": 1,
                    "class": "top"
                }
            ]
        },
        {
            "class": "LargeSofa",
            "confidence": 0.9393718242645264,
            "x": 442.96099853515625,
            "y": 344.3905029296875,
            "width": 27.201690673828125,
            "height": 34.851226806640625,
            "keypoints": [
                {
                    "x": 453.67877197265625,
                    "y": 344.81854248046875,
                    "confidence": 0.9999477863311768,
                    "class_id": 0,
                    "class": "bottom"
                },
                {
                    "x": 431.30670166015625,
                    "y": 344.21759033203125,
                    "confidence": 0.9999139308929443,
                    "class_id": 1,
                    "class": "top"
                }
            ]
        },
        {
            "class": "LargeSofa",
            "confidence": 0.9392716884613037,
            "x": 444.5066223144531,
            "y": 511.4659423828125,
            "width": 20.7601318359375,
            "height": 48.215576171875,
            "keypoints": [
                {
                    "x": 453.835205078125,
                    "y": 514.2199096679688,
                    "confidence": 0.9999434947967529,
                    "class_id": 0,
                    "class": "bottom"
                },
                {
                    "x": 436.93017578125,
                    "y": 513.6806640625,
                    "confidence": 0.9999774694442749,
                    "class_id": 1,
                    "class": "top"
                }
            ]
        },
        {
            "class": "ToiletSeat",
            "confidence": 0.9376240968704224,
            "x": 408.20294189453125,
            "y": 414.1845703125,
            "width": 25.945831298828125,
            "height": 32.4906005859375,
            "keypoints": [
                {
                    "x": 396.6824951171875,
                    "y": 412.09783935546875,
                    "confidence": 0.9999533891677856,
                    "class_id": 0,
                    "class": "bottom"
                },
                {
                    "x": 421.5591735839844,
                    "y": 411.97686767578125,
                    "confidence": 0.9999768733978271,
                    "class_id": 1,
                    "class": "top"
                }
            ]
        },
        {
            "class": "SideTable",
            "confidence": 0.9324320554733276,
            "x": 444.2750244140625,
            "y": 443.0787353515625,
            "width": 21.239532470703125,
            "height": 21.825225830078125,
            "keypoints": [
                {
                    "x": 443.61907958984375,
                    "y": 442.9870910644531,
                    "confidence": 0.9996316432952881,
                    "class_id": 0,
                    "class": "keypoint_0"
                },
                {
                    "x": 0.0,
                    "y": 0.0,
                    "confidence": 0.00020437026978470385,
                    "class_id": 1,
                    "class": "keypoint_1"
                }
            ]
        },
        {
            "class": "ArmChair",
            "confidence": 0.9323530793190002,
            "x": 164.02793884277344,
            "y": 275.78399658203125,
            "width": 34.141815185546875,
            "height": 24.873992919921875,
            "keypoints": [
                {
                    "x": 162.3079071044922,
                    "y": 264.946533203125,
                    "confidence": 0.9999260902404785,
                    "class_id": 0,
                    "class": "bottom"
                },
                {
                    "x": 161.98876953125,
                    "y": 286.9169921875,
                    "confidence": 0.9999638795852661,
                    "class_id": 1,
                    "class": "top"
                }
            ]
        },
        {
            "class": "WashBasin",
            "confidence": 0.9319692850112915,
            "x": 126.98558807373047,
            "y": 441.40447998046875,
            "width": 21.852249145507812,
            "height": 77.640869140625,
            "keypoints": [
                {
                    "x": 115.57164001464844,
                    "y": 437.2375793457031,
                    "confidence": 0.9999052286148071,
                    "class_id": 0,
                    "class": "bottom"
                },
                {
                    "x": 132.32083129882812,
                    "y": 434.9097595214844,
                    "confidence": 0.9999010562896729,
                    "class_id": 1,
                    "class": "top"
                }
            ]
        },
        {
            "class": "ToiletSeat",
            "confidence": 0.9316301941871643,
            "x": 72.05233001708984,
            "y": 463.777587890625,
            "width": 23.998485565185547,
            "height": 36.483917236328125,
            "keypoints": [
                {
                    "x": 81.23770904541016,
                    "y": 463.71832275390625,
                    "confidence": 0.999953031539917,
                    "class_id": 0,
                    "class": "bottom"
                },
                {
                    "x": 63.38977813720703,
                    "y": 464.91204833984375,
                    "confidence": 0.999937891960144,
                    "class_id": 1,
                    "class": "top"
                }
            ]
        },
        {
            "class": "CenterTable",
            "confidence": 0.9310829043388367,
            "x": 470.9557189941406,
            "y": 512.796630859375,
            "width": 23.43084716796875,
            "height": 28.660919189453125,
            "keypoints": [
                {
                    "x": 470.67486572265625,
                    "y": 512.6092529296875,
                    "confidence": 0.9996286630630493,
                    "class_id": 0,
                    "class": "keypoint_0"
                },
                {
                    "x": 0.0,
                    "y": 0.0,
                    "confidence": 0.00013432366540655494,
                    "class_id": 1,
                    "class": "keypoint_1"
                }
            ]
        },
        {
            "class": "SideTable",
            "confidence": 0.9306402802467346,
            "x": 440.9759521484375,
            "y": 240.65621948242188,
            "width": 21.7825927734375,
            "height": 22.308181762695312,
            "keypoints": [
                {
                    "x": 441.11639404296875,
                    "y": 240.81631469726562,
                    "confidence": 0.9994624257087708,
                    "class_id": 0,
                    "class": "keypoint_0"
                },
                {
                    "x": 0.0,
                    "y": 0.0,
                    "confidence": 0.0005755701567977667,
                    "class_id": 1,
                    "class": "keypoint_1"
                }
            ]
        },
        {
            "class": "LargeSofa",
            "confidence": 0.9306315779685974,
            "x": 509.8038330078125,
            "y": 322.083984375,
            "width": 33.104339599609375,
            "height": 26.19671630859375,
            "keypoints": [
                {
                    "x": 509.7190856933594,
                    "y": 333.8177490234375,
                    "confidence": 0.9998606443405151,
                    "class_id": 0,
                    "class": "bottom"
                },
                {
                    "x": 509.5368957519531,
                    "y": 309.88787841796875,
                    "confidence": 0.9998958110809326,
                    "class_id": 1,
                    "class": "top"
                }
            ]
        },
        {
            "class": "GasStove",
            "confidence": 0.9302158951759338,
            "x": 572.1570434570312,
            "y": 203.4766845703125,
            "width": 17.689697265625,
            "height": 20.741897583007812,
            "keypoints": [
                {
                    "x": 565.7891845703125,
                    "y": 203.1074981689453,
                    "confidence": 0.9996470212936401,
                    "class_id": 0,
                    "class": "top"
                },
                {
                    "x": 578.922607421875,
                    "y": 202.96949768066406,
                    "confidence": 0.9993892908096313,
                    "class_id": 1,
                    "class": "bottom"
                }
            ]
        },
        {
            "class": "ToiletSeat",
            "confidence": 0.9293232560157776,
            "x": 648.1405029296875,
            "y": 226.37359619140625,
            "width": 20.2554931640625,
            "height": 21.890914916992188,
            "keypoints": [
                {
                    "x": 657.059326171875,
                    "y": 226.1157684326172,
                    "confidence": 0.999718964099884,
                    "class_id": 0,
                    "class": "bottom"
                },
                {
                    "x": 637.995849609375,
                    "y": 224.82659912109375,
                    "confidence": 0.9996236562728882,
                    "class_id": 1,
                    "class": "top"
                }
            ]
        },
        {
            "class": "WashBasin",
            "confidence": 0.9289826154708862,
            "x": 414.309814453125,
            "y": 385.413330078125,
            "width": 15.597259521484375,
            "height": 29.88299560546875,
            "keypoints": [
                {
                    "x": 407.1620178222656,
                    "y": 385.158935546875,
                    "confidence": 0.9997873902320862,
                    "class_id": 0,
                    "class": "bottom"
                },
                {
                    "x": 421.5610656738281,
                    "y": 385.4925842285156,
                    "confidence": 0.9998775720596313,
                    "class_id": 1,
                    "class": "top"
                }
            ]
        },
        {
            "class": "GasStove",
            "confidence": 0.9284529089927673,
            "x": 686.8534545898438,
            "y": 121.68035888671875,
            "width": 15.4224853515625,
            "height": 10.508750915527344,
            "keypoints": [
                {
                    "x": 685.9766235351562,
                    "y": 115.00532531738281,
                    "confidence": 0.9986000657081604,
                    "class_id": 0,
                    "class": "top"
                },
                {
                    "x": 686.03125,
                    "y": 126.0953140258789,
                    "confidence": 0.9969096779823303,
                    "class_id": 1,
                    "class": "bottom"
                }
            ]
        },
        {
            "class": "wardrobe",
            "confidence": 0.9244335889816284,
            "x": 69.80587768554688,
            "y": 349.01953125,
            "width": 19.987491607666016,
            "height": 113.53482055664062,
            "keypoints": [
                {
                    "x": 60.498477935791016,
                    "y": 347.3894958496094,
                    "confidence": 0.9999116659164429,
                    "class_id": 0,
                    "class": "top"
                },
                {
                    "x": 76.03678131103516,
                    "y": 348.7664794921875,
                    "confidence": 0.9999295473098755,
                    "class_id": 1,
                    "class": "bottom"
                }
            ]
        },
        {
            "class": "WashBasin",
            "confidence": 0.9242948293685913,
            "x": 644.0145263671875,
            "y": 205.4182586669922,
            "width": 14.04345703125,
            "height": 21.82562255859375,
            "keypoints": [
                {
                    "x": 650.69677734375,
                    "y": 203.95806884765625,
                    "confidence": 0.998830258846283,
                    "class_id": 0,
                    "class": "bottom"
                },
                {
                    "x": 635.653076171875,
                    "y": 204.60260009765625,
                    "confidence": 0.9991922974586487,
                    "class_id": 1,
                    "class": "top"
                }
            ]
        },
        {
            "class": "tv",
            "confidence": 0.9218282103538513,
            "x": 243.77272033691406,
            "y": 186.42901611328125,
            "width": 16.559356689453125,
            "height": 50.56755065917969,
            "keypoints": [
                {
                    "x": 248.01416015625,
                    "y": 175.78433227539062,
                    "confidence": 0.9999798536300659,
                    "class_id": 0,
                    "class": "keypoint_0"
                },
                {
                    "x": 237.05616760253906,
                    "y": 175.02252197265625,
                    "confidence": 0.9999549388885498,
                    "class_id": 1,
                    "class": "keypoint_1"
                }
            ]
        },
        {
            "class": "tv",
            "confidence": 0.9194731116294861,
            "x": 362.1930847167969,
            "y": 154.15872192382812,
            "width": 10.9791259765625,
            "height": 72.04228210449219,
            "keypoints": [
                {
                    "x": 365.63702392578125,
                    "y": 155.57513427734375,
                    "confidence": 0.9999343156814575,
                    "class_id": 0,
                    "class": "keypoint_0"
                },
                {
                    "x": 358.3388366699219,
                    "y": 155.7684783935547,
                    "confidence": 0.9999184608459473,
                    "class_id": 1,
                    "class": "keypoint_1"
                }
            ]
        },
        {
            "class": "ToiletSeat",
            "confidence": 0.9172966480255127,
            "x": 68.82150268554688,
            "y": 114.7362060546875,
            "width": 23.690692901611328,
            "height": 30.869140625,
            "keypoints": [
                {
                    "x": 82.43994140625,
                    "y": 115.1221694946289,
                    "confidence": 0.999954104423523,
                    "class_id": 0,
                    "class": "bottom"
                },
                {
                    "x": 59.82840347290039,
                    "y": 114.92869567871094,
                    "confidence": 0.9999111890792847,
                    "class_id": 1,
                    "class": "top"
                }
            ]
        },
        {
            "class": "sink",
            "confidence": 0.9153600931167603,
            "x": 648.38525390625,
            "y": 120.36760711669922,
            "width": 11.29730224609375,
            "height": 14.861923217773438,
            "keypoints": [
                {
                    "x": 648.1044921875,
                    "y": 120.41080474853516,
                    "confidence": 0.9996968507766724,
                    "class_id": 0,
                    "class": "keypoint_0"
                },
                {
                    "x": 0.0,
                    "y": 0.0,
                    "confidence": 6.305037095444277e-05,
                    "class_id": 1,
                    "class": "keypoint_1"
                }
            ]
        },
        {
            "class": "tv",
            "confidence": 0.9109747409820557,
            "x": 363.5732421875,
            "y": 397.2098693847656,
            "width": 14.763031005859375,
            "height": 51.33917236328125,
            "keypoints": [
                {
                    "x": 366.2312316894531,
                    "y": 407.7297668457031,
                    "confidence": 0.9999333620071411,
                    "class_id": 0,
                    "class": "keypoint_0"
                },
                {
                    "x": 357.30120849609375,
                    "y": 407.1632080078125,
                    "confidence": 0.9999098777770996,
                    "class_id": 1,
                    "class": "keypoint_1"
                }
            ]
        },
        {
            "class": "tv",
            "confidence": 0.909294068813324,
            "x": 619.6981201171875,
            "y": 381.08721923828125,
            "width": 16.65789794921875,
            "height": 110.140869140625,
            "keypoints": [
                {
                    "x": 625.6035766601562,
                    "y": 372.90673828125,
                    "confidence": 0.9999480247497559,
                    "class_id": 0,
                    "class": "keypoint_0"
                },
                {
                    "x": 614.1133422851562,
                    "y": 372.2933654785156,
                    "confidence": 0.999968409538269,
                    "class_id": 1,
                    "class": "keypoint_1"
                }
            ]
        },
        {
            "class": "tv",
            "confidence": 0.8766682744026184,
            "x": 245.0496826171875,
            "y": 402.46173095703125,
            "width": 11.80926513671875,
            "height": 113.42010498046875,
            "keypoints": [
                {
                    "x": 250.21804809570312,
                    "y": 389.4391784667969,
                    "confidence": 0.9999761581420898,
                    "class_id": 0,
                    "class": "keypoint_0"
                },
                {
                    "x": 239.2595672607422,
                    "y": 389.0027160644531,
                    "confidence": 0.9999527931213379,
                    "class_id": 1,
                    "class": "keypoint_1"
                }
            ]
        },
        {
            "class": "wardrobe",
            "confidence": 0.034681547433137894,
            "x": 686.120361328125,
            "y": 237.9656219482422,
            "width": 15.44158935546875,
            "height": 35.1201171875,
            "keypoints": [
                {
                    "x": 683.2006225585938,
                    "y": 236.19654846191406,
                    "confidence": 0.9992054104804993,
                    "class_id": 0,
                    "class": "top"
                },
                {
                    "x": 688.6879272460938,
                    "y": 235.7647247314453,
                    "confidence": 0.9946140646934509,
                    "class_id": 1,
                    "class": "bottom"
                }
            ]
        }
    ]
}